HISTORY.rst
LICENSE
MANIFEST.in
README.md
setup.cfg
setup.py
test_eco.py
tox.ini
eco/__init__.py
eco/eco.js
eco.egg-info/PKG-INFO
eco.egg-info/SOURCES.txt
eco.egg-info/dependency_links.txt
eco.egg-info/requires.txt
eco.egg-info/top_level.txt